littleflow_redis/__init__.py
littleflow_redis/__main__.py
littleflow_redis/cli.py
littleflow_redis/context.py
littleflow_redis/remote.py
littleflow_redis/wait.py
littleflow_redis/console/__init__.py
littleflow_redis/console/__main__.py
littleflow_redis/console/cli.py
littleflow_redis/console/service.py
littleflow_redis/console/assets/css/__init__.py
littleflow_redis/console/assets/css/site.css
littleflow_redis/console/assets/css/uikit-rtl.css
littleflow_redis/console/assets/css/uikit-rtl.min.css
littleflow_redis/console/assets/css/uikit.css
littleflow_redis/console/assets/css/uikit.min.css
littleflow_redis/console/assets/js/__init__.py
littleflow_redis/console/assets/js/app.js
littleflow_redis/console/assets/js/jquery-3.6.0.min.js
littleflow_redis/console/assets/js/svg-pan-zoom.js
littleflow_redis/console/assets/js/uikit-icons.js
littleflow_redis/console/assets/js/uikit-icons.min.js
littleflow_redis/console/assets/js/uikit.js
littleflow_redis/console/assets/js/uikit.min.js
littleflow_redis/console/templates/__init__.py
littleflow_redis/console/templates/index.html
littleflow_redis/service/__init__.py
littleflow_redis/service/__main__.py
littleflow_redis/service/cli.py
littleflow_redis/service/service.py
littleflow_redis-0.4.0.dist-info/METADATA
littleflow_redis-0.4.0.dist-info/WHEEL
littleflow_redis-0.4.0.dist-info/top_level.txt
littleflow_redis-0.4.0.dist-info/RECORD
