Metadata-Version: 2.1
Name: littleflow-redis
Version: 0.4.0
Summary: An integration of littleflow an Redis for remote execution.
Home-page: https://github.com/alexmilowski/littleflow
Author: Alex Miłowski
Author-email: alex@milowski.com
License: Apache License 2.0
Requires-Dist: littleflow
Requires-Dist: rqse
Requires-Dist: Flask
Requires-Dist: click
Requires-Dist: flasgger
Requires-Dist: pyyaml
Requires-Dist: requests
Requires-Dist: boto3
